{
  "cli": {
    "version": ">= 16.7.0",
    "appVersionSource": "remote"
  },
  "build": {
    "development": {
      "developmentClient": true,
      "distribution": "internal",
      "ios": {
        "resourceClass": "m-medium"
      }
    },
    "preview": {
      "distribution": "internal",
      "ios": {
        "resourceClass": "m-medium"
      }
    },
    "production": {
      "autoIncrement": true,
      "ios": {
        "resourceClass": "m-medium",
        "buildConfiguration": "Release",
        "cache": {
          "key": "cache-invalidate-2024-01"
        }
      },
      "env": {
        "EXPO_PUBLIC_SUPABASE_URL": "$EXPO_PUBLIC_SUPABASE_URL",
        "EXPO_PUBLIC_SUPABASE_ANON_KEY": "$EXPO_PUBLIC_SUPABASE_ANON_KEY"
      }
    }
  },
  "submit": {
    "production": {
      "ios": {
        "appleId": "abdullaehsan2002@gmail.com",
        "ascAppId": "6746690850",
        "appleTeamId": "45274ZPL7M"
      }
    }
  }
}
